signal_cli_rest_api/__init__.py
signal_cli_rest_api/api/__init__.py
signal_cli_rest_api/api/block.py
signal_cli_rest_api/api/groups.py
signal_cli_rest_api/api/messages.py
signal_cli_rest_api/api/profile.py
signal_cli_rest_api/api/register.py
signal_cli_rest_api/config.py
signal_cli_rest_api/main.py
signal_cli_rest_api/schemas.py
signal_cli_rest_api/utils.py
signal_cli_rest_api-0.2.0.dist-info/LICENSE
signal_cli_rest_api-0.2.0.dist-info/WHEEL
signal_cli_rest_api-0.2.0.dist-info/METADATA
signal_cli_rest_api-0.2.0.dist-info/RECORD
