Metadata-Version: 2.1
Name: signal-cli-rest-api
Version: 0.2.0
Summary: 
Home-page: https://github.com/SebastianLuebke/signal-cli-rest-api
Author: Sebastian Noel Lübke
Author-email: sebastian@luebke.io
Requires-Python: >=3.8,<3.9
Classifier: Programming Language :: Python :: 3
Classifier: Programming Language :: Python :: 3.8
Requires-Dist: aiofiles (>=0.6.0,<0.7.0)
Requires-Dist: fastapi (>=0.58.0,<0.59.0)
Requires-Dist: httpx (>=0.16.1,<0.17.0)
Requires-Dist: pypng (>=0.0.20,<0.0.21)
Requires-Dist: pyqrcode (>=1.2.1,<2.0.0)
Requires-Dist: python-jose (>=3.1.0,<4.0.0)
Requires-Dist: uvicorn (>=0.11.5,<0.12.0)
Project-URL: Repository, https://github.com/SebastianLuebke/signal-cli-rest-api
